pacman/__init__.py
pacman/_version.py
pacman/config_setup.py
pacman/exceptions.py
pacman/pacman.cfg
pacman/py.typed
pacman/data/__init__.py
pacman/data/pacman_data_view.py
pacman/data/pacman_data_writer.py
pacman/model/__init__.py
pacman/model/graphs/__init__.py
pacman/model/graphs/abstract_edge.py
pacman/model/graphs/abstract_edge_partition.py
pacman/model/graphs/abstract_multiple_partition.py
pacman/model/graphs/abstract_single_source_partition.py
pacman/model/graphs/abstract_supports_sdram_edges.py
pacman/model/graphs/abstract_vertex.py
pacman/model/graphs/abstract_virtual.py
pacman/model/graphs/application/__init__.py
pacman/model/graphs/application/application_2d_fpga_vertex.py
pacman/model/graphs/application/application_2d_spinnaker_link_vertex.py
pacman/model/graphs/application/application_edge.py
pacman/model/graphs/application/application_edge_partition.py
pacman/model/graphs/application/application_fpga_vertex.py
pacman/model/graphs/application/application_graph.py
pacman/model/graphs/application/application_spinnaker_link_vertex.py
pacman/model/graphs/application/application_vertex.py
pacman/model/graphs/application/application_virtual_vertex.py
pacman/model/graphs/application/fpga_connection.py
pacman/model/graphs/application/abstract/__init__.py
pacman/model/graphs/application/abstract/abstract_2d_device_vertex.py
pacman/model/graphs/application/abstract/abstract_one_app_one_machine_vertex.py
pacman/model/graphs/common/__init__.py
pacman/model/graphs/common/chip_and_core.py
pacman/model/graphs/common/edge_traffic_type.py
pacman/model/graphs/common/mdslice.py
pacman/model/graphs/common/slice.py
pacman/model/graphs/machine/__init__.py
pacman/model/graphs/machine/abstract_sdram_partition.py
pacman/model/graphs/machine/constant_sdram_machine_partition.py
pacman/model/graphs/machine/destination_segmented_sdram_machine_partition.py
pacman/model/graphs/machine/machine_edge.py
pacman/model/graphs/machine/machine_fpga_vertex.py
spinnaker_pacman-1!7.4.0.dist-info/licenses/LICENSE
spinnaker_pacman-1!7.4.0.dist-info/licenses/LICENSE_POLICY.md
spinnaker_pacman-1!7.4.0.dist-info/METADATA
spinnaker_pacman-1!7.4.0.dist-info/WHEEL
spinnaker_pacman-1!7.4.0.dist-info/top_level.txt
spinnaker_pacman-1!7.4.0.dist-info/zip-safe
spinnaker_pacman-1!7.4.0.dist-info/RECORD
