Metadata-Version: 2.4
Name: SpiNNaker_PACMAN
Version: 1!7.4.0
Summary: Partition and Configuration Manager
Home-page: https://github.com/SpiNNakerManchester/PACMAN
Maintainer: SpiNNakerTeam
Maintainer-email: spinnakerusers@googlegroups.com
License: Apache-2.0
Keywords: spinnaker,routing,partitioning,placement
Classifier: Development Status :: 5 - Production/Stable
Classifier: Intended Audience :: Developers
Classifier: Intended Audience :: Science/Research
Classifier: Natural Language :: English
Classifier: Operating System :: POSIX :: Linux
Classifier: Operating System :: Microsoft :: Windows
Classifier: Operating System :: MacOS
Classifier: Programming Language :: Python :: 3
Classifier: Programming Language :: Python :: 3.8
Classifier: Programming Language :: Python :: 3.9
Classifier: Programming Language :: Python :: 3.10
Classifier: Programming Language :: Python :: 3.11
Classifier: Programming Language :: Python :: 3.12
Classifier: Programming Language :: Python :: 3.13
Requires-Python: <4,>=3.8
License-File: LICENSE
License-File: LICENSE_POLICY.md
Requires-Dist: jsonschema
Requires-Dist: deprecated
Requires-Dist: SpiNNUtilities==1!7.4.0
Requires-Dist: SpiNNMachine==1!7.4.0
Provides-Extra: test
Requires-Dist: pytest-cov; extra == "test"
Requires-Dist: pylint; extra == "test"
Requires-Dist: testfixtures; extra == "test"
Requires-Dist: types-jsonschema; extra == "test"
Requires-Dist: types-Deprecated; extra == "test"
Provides-Extra: draw-placements
Requires-Dist: spinner; extra == "draw-placements"
Dynamic: license-file
